houston/__init__.py
houston/cli.py
houston/controller.py
houston/files.py
houston/utils.py
houston-0.3.0.dist-info/DESCRIPTION.rst
houston-0.3.0.dist-info/entry_points.txt
houston-0.3.0.dist-info/METADATA
houston-0.3.0.dist-info/metadata.json
houston-0.3.0.dist-info/RECORD
houston-0.3.0.dist-info/top_level.txt
houston-0.3.0.dist-info/WHEEL
houston-0.3.0.dist-info/zip-safe
