Metadata-Version: 2.0
Name: houston
Version: 0.3.0
Summary: Application deployment on CoreOS clusters using fleetd and Consul
Home-page: http://houston.readthedocs.org
Author: Gavin M. Roy
Author-email: gavinr@aweber.com
License: BSD
Platform: UNKNOWN
Classifier: Development Status :: 3 - Alpha
Classifier: Environment :: Console
Classifier: Intended Audience :: Developers
Classifier: License :: OSI Approved :: BSD License
Classifier: Operating System :: OS Independent
Classifier: Programming Language :: Python :: 2
Classifier: Programming Language :: Python :: 2.6
Classifier: Programming Language :: Python :: 2.7
Classifier: Programming Language :: Python :: 3
Classifier: Programming Language :: Python :: 3.2
Classifier: Programming Language :: Python :: 3.3
Classifier: Programming Language :: Python :: 3.4
Classifier: Programming Language :: Python :: Implementation :: CPython
Classifier: Programming Language :: Python :: Implementation :: PyPy
Classifier: Topic :: Communications
Classifier: Topic :: Internet
Classifier: Topic :: System :: Boot :: Init
Classifier: Topic :: System :: Clustering
Classifier: Topic :: System :: Operating System
Classifier: Topic :: System :: Software Distribution
Requires-Dist: consulate
Requires-Dist: fleetpy
Requires-Dist: pyyaml
